hspy_utils/CondAns.py
hspy_utils/HspyPrep.py
hspy_utils/__init__.py
hspy_utils-0.1.0.dist-info/METADATA
hspy_utils-0.1.0.dist-info/WHEEL
hspy_utils-0.1.0.dist-info/top_level.txt
hspy_utils-0.1.0.dist-info/RECORD
