Metadata-Version: 2.4
Name: hspy_utils
Version: 0.1.0
Summary: A utility package including CondAns and HspyPrep modules.
Home-page: https://example.com
Author: Mohammadreza Hassanzadeh
Author-email: mohammadreza.hassanzadeh@epfl.ch
Classifier: Programming Language :: Python :: 3
Classifier: Operating System :: OS Independent
Requires-Python: >=3.6
Requires-Dist: numpy
Requires-Dist: scipy
Requires-Dist: matplotlib
Requires-Dist: lmfit
Requires-Dist: lumispy
Requires-Dist: hyperspy
Dynamic: author
Dynamic: author-email
Dynamic: classifier
Dynamic: home-page
Dynamic: requires-dist
Dynamic: requires-python
Dynamic: summary
